minelog/__init__.py
minelog/__main__.py
minelog/cli.py
minelog/core.py
minelog/info.py
minelog/py.typed
minelog-0.0.1.dist-info/METADATA
minelog-0.0.1.dist-info/WHEEL
minelog-0.0.1.dist-info/entry_points.txt
minelog-0.0.1.dist-info/licenses/LICENSE
minelog-0.0.1.dist-info/RECORD
