Metadata-Version: 2.4
Name: minelog
Version: 0.0.1
Summary: Script for query easily your minecraft logs.
Project-URL: Homepage, https://github.com/Dashstrom/minelog
Project-URL: Repository, https://github.com/Dashstrom/minelog
Project-URL: Documentation, https://dashstrom.github.io/minelog
Author-email: Dashstrom <dashstrom.pro@gmail.com>
License-File: LICENSE
Keywords: python
Classifier: Development Status :: 3 - Alpha
Classifier: Environment :: Console
Classifier: Framework :: Pytest
Classifier: Framework :: Sphinx
Classifier: Intended Audience :: Developers
Classifier: Intended Audience :: System Administrators
Classifier: License :: OSI Approved :: MIT License
Classifier: Natural Language :: English
Classifier: Operating System :: OS Independent
Classifier: Programming Language :: Python :: 3
Classifier: Programming Language :: Python :: 3 :: Only
Classifier: Programming Language :: Python :: 3.9
Classifier: Programming Language :: Python :: 3.10
Classifier: Programming Language :: Python :: 3.11
Classifier: Programming Language :: Python :: 3.12
Classifier: Programming Language :: Python :: 3.13
Classifier: Typing :: Typed
Requires-Python: <4.0,>=3.9
Requires-Dist: click>=8.1.0
Requires-Dist: typing-extensions>=4.8.0
